scheduleplus/cronparser.py
scheduleplus/job.py
scheduleplus/scheduler.py
scheduleplus/text_table.py
scheduleplus-0.1.2.dist-info/LICENSE
scheduleplus-0.1.2.dist-info/METADATA
scheduleplus-0.1.2.dist-info/WHEEL
scheduleplus-0.1.2.dist-info/top_level.txt
scheduleplus-0.1.2.dist-info/RECORD
